{
    "configurations": [
        {
            "name": "STM32",
            "includePath": [
                "${workspaceFolder}/**",
                "${workspaceFolder}/**",
                "${workspaceFolder}/Core/Inc",
                "${workspaceFolder}/Drivers/STM32F4xx_HAL_Driver/Inc",
                "${workspaceFolder}/Drivers/STM32F4xx_HAL_Driver/Inc/Legacy"
            ],
            "defines": [
                "_DEBUG",
                "UNICODE",
                "_UNICODE",
                "STM32F407xx",
                "USE_HAL_DRIVER"
            ],
            "compilerPath": "D:\\Arquivos de Programas\\mingw64\\bin\\gcc.exe",
            "cStandard": "c17",
            "cppStandard": "gnu++14",
            "intelliSenseMode": "gcc-arm"
        }
    ],
    "version": 4
}